pytmcl_gideonrab/TMCLCommands.json
pytmcl_gideonrab/__init__.py
pytmcl_gideonrab/exceptions.py
pytmcl_gideonrab/tmcl_board.py
pytmcl_gideonrab/tmcl_gpio.py
pytmcl_gideonrab/tmcl_motion.py
pytmcl_gideonrab-0.1.0.dist-info/LICENSE
pytmcl_gideonrab-0.1.0.dist-info/WHEEL
pytmcl_gideonrab-0.1.0.dist-info/METADATA
pytmcl_gideonrab-0.1.0.dist-info/RECORD
