Metadata-Version: 2.1
Name: pytmcl_gideonrab
Version: 0.1.0
Summary: Python library for automation cells.
Author-email: Gideon Rabson <grabson@pendar.com>
Requires-Python: >=3.7
Classifier: Programming Language :: Python :: 3
Classifier: Operating System :: Microsoft
Requires-Dist: pyserial
Requires-Dist: numpy
Project-URL: Source, http://gitlab.pendar.local/production/automationlib
